naveen/__init__.py
naveen/__version__.py
naveen/logger.py
naveen/naveen.py
naveen/data/__init__.py
naveen/data/filter.py
naveen/data/page_maker.py
naveen/data/pipe_cleaner.py
naveen/data/url_streamer.py
naveen/data/scrapers/__init__.py
naveen/data/scrapers/html_extractor.py
naveen/data/scrapers/html_tag_stripper.py
naveen/experiment/__init__.py
naveen/experiment/experiment.py
naveen/experiment/experiment_finisher.py
naveen/experiment/experiment_group_runner.py
naveen/experiment/experiment_runner.py
naveen/experiment/experiment_writer.py
naveen/experiment/config/__init__.py
naveen/experiment/config/abstract_config.py
naveen/experiment/config/config_validator.py
naveen/experiment/config/dynamic_experiment_config_maker.py
naveen/experiment/config/experiment_group_parser.py
naveen/experiment/config/experiment_parameter.py
naveen/experiment/config/model_string_manager.py
naveen/utils/__init__.py
naveen/utils/ngram_maker.py
naveen/utils/readers.py
naveen-0.3.7.dist-info/METADATA
naveen-0.3.7.dist-info/WHEEL
naveen-0.3.7.dist-info/entry_points.txt
naveen-0.3.7.dist-info/top_level.txt
naveen-0.3.7.dist-info/RECORD
