Metadata-Version: 2.1
Name: naveen
Version: 0.3.7
Requires-Dist: bs4
Requires-Dist: numpy
Requires-Dist: pandas
Requires-Dist: pyyaml
